{
  "@context": [
    "https://www.w3.org/ns/did/v1",
    "https://w3id.org/security/suites/jws-2020/v1"
  ],
  "id": "did:web:msterle.github.io:dids:alice",
  "verificationMethod": [
    {
      "id": "did:web:msterle.github.io:dids:alice#owner",
      "type": "JsonWebKey2020",
      "controller": "did:web:msterle.github.io:dids:alice",
      "publicKeyJwk": {
        "kty": "OKP",
        "crv": "Ed25519",
        "x": "4zqlEVbhq9zShjGlLfGKSRt9pdUBKETvl9YYeuEgWng"
      }
    }
  ],
  "authentication": ["did:web:msterle.github.io:dids:alice#owner"],
  "assertionMethod": ["did:web:msterle.github.io:dids:alice#owner"],
  "service": [{
    "id": "did:web:msterle.github.io:dids:alice#did-communication",
    "type": "did-communication",
    "priority" : 0,
    "recipientKeys" : [ "did:web:msterle.github.io:dids:alice#owner" ],
    "routingKeys" : [],
    "accept": [
      "didcomm/aip1"
    ],
    "serviceEndpoint": "http://localhost:5002"
  }]
}
